scimpy/__init__.py
scimpy/centralplotui.py
scimpy/impfitterui.py
scimpy/imptesterui.py
scimpy/progressmodal.py
scimpy/scimpyui.py
scimpy/speakermodel.py
scimpy/speakermodelui.py
scimpy/speakertest.py
scimpy-0.0.dev1.dist-info/DESCRIPTION.rst
scimpy-0.0.dev1.dist-info/METADATA
scimpy-0.0.dev1.dist-info/RECORD
scimpy-0.0.dev1.dist-info/WHEEL
scimpy-0.0.dev1.dist-info/entry_points.txt
scimpy-0.0.dev1.dist-info/metadata.json
scimpy-0.0.dev1.dist-info/top_level.txt
